LICENSE
MANIFEST.in
README.rst
requirements.txt
setup.cfg
setup.py
django_openauth.egg-info/PKG-INFO
django_openauth.egg-info/SOURCES.txt
django_openauth.egg-info/dependency_links.txt
django_openauth.egg-info/requires.txt
django_openauth.egg-info/top_level.txt
openauth/__init__.py
openauth/admin.py
openauth/apps.py
openauth/models.py
openauth/settings.py
openauth/tests.py
openauth/urls.py
openauth/views.py
openauth/migrations/0001_initial.py
openauth/migrations/__init__.py
openauth/templates/admin/login.html
openauth/templates/registration/login.html