Metadata-Version: 1.1
Name: django-openauth
Version: 0.3.1
Summary: 统一认证平台的 django 插件
Home-page: https://github.com/daimon99/django-openauth
Author: Jian Dai
Author-email: daijian1@qq.com
License: Apache Software License 2.0 (Apache-2.0)
Platform: UNKNOWN
Classifier: Environment :: Web Environment
Classifier: Framework :: Django
Classifier: Framework :: Django :: 2.0
Classifier: Intended Audience :: Developers
Classifier: Operating System :: OS Independent
Classifier: Programming Language :: Python
Classifier: Programming Language :: Python :: 3
Classifier: Programming Language :: Python :: 3 :: Only
Classifier: Programming Language :: Python :: 3.6
Classifier: Programming Language :: Python :: 3.7
Classifier: Programming Language :: Python :: 3.8
Classifier: Topic :: Internet :: WWW/HTTP
Classifier: Topic :: Internet :: WWW/HTTP :: Dynamic Content
